icron/__init__.py
icron/croniter.py
tests/__init__.py
tests/test_croniter.py
python_icron-3.0.1.dist-info/LICENSE
python_icron-3.0.1.dist-info/METADATA
python_icron-3.0.1.dist-info/WHEEL
python_icron-3.0.1.dist-info/top_level.txt
python_icron-3.0.1.dist-info/RECORD
