Metadata-Version: 2.1
Name: python-icron
Version: 3.0.1
Summary: icron provides iteration for datetime object with cron like format
Home-page: https://hg.sr.ht/~pythonian/icron
Author: Matsumoto Taichi, kiorky, Aurélien Campéas
Author-email: taichino@gmail.com, kiorky@cryptelium.net, aurelien.campeas@pythonian.fr
License: MIT License
Keywords: datetime,iterator,cron
Classifier: Development Status :: 4 - Beta
Classifier: Intended Audience :: Developers
Classifier: License :: OSI Approved :: MIT License
Classifier: Operating System :: POSIX
Classifier: Programming Language :: Python
Classifier: Programming Language :: Python :: 3
Classifier: Topic :: Software Development :: Libraries :: Python Modules
Requires-Python: >=3.9
License-File: LICENSE
Requires-Dist: python-dateutil
Requires-Dist: pytz >2021.1
